{
  "main": {
    "id": "04c24765d7cc576a",
    "type": "split",
    "children": [
      {
        "id": "275f7987b79b8030",
        "type": "tabs",
        "children": [
          {
            "id": "46809242ae41aa57",
            "type": "leaf",
            "state": {
              "type": "markdown",
              "state": {
                "file": "Areas/English/Interacting with people at work/Clear and to the point.md",
                "mode": "source",
                "source": false
              },
              "icon": "lucide-file",
              "title": "Clear and to the point"
            }
          }
        ]
      }
    ],
    "direction": "vertical"
  },
  "left": {
    "id": "26af04220efc3209",
    "type": "split",
    "children": [
      {
        "id": "d04d1c7140d2226f",
        "type": "tabs",
        "children": [
          {
            "id": "9cfaa0d3379dbe21",
            "type": "leaf",
            "state": {
              "type": "file-explorer",
              "state": {
                "sortOrder": "alphabetical"
              },
              "icon": "lucide-folder-closed",
              "title": "Files"
            }
          },
          {
            "id": "f25229b2fc9c2bdc",
            "type": "leaf",
            "state": {
              "type": "search",
              "state": {
                "query": "",
                "matchingCase": false,
                "explainSearch": false,
                "collapseAll": false,
                "extraContext": false,
                "sortOrder": "alphabetical"
              },
              "icon": "lucide-search",
              "title": "Search"
            }
          },
          {
            "id": "6fe0004cac2b481d",
            "type": "leaf",
            "state": {
              "type": "bookmarks",
              "state": {},
              "icon": "lucide-bookmark",
              "title": "Bookmarks"
            }
          }
        ]
      }
    ],
    "direction": "horizontal",
    "width": 291.5,
    "collapsed": true
  },
  "right": {
    "id": "a17d2679f8f0aa31",
    "type": "split",
    "children": [
      {
        "id": "ee42da24fec77ee0",
        "type": "tabs",
        "children": [
          {
            "id": "a13d0028cd0e6b7f",
            "type": "leaf",
            "state": {
              "type": "backlink",
              "state": {
                "file": "Programs/JS-Performance/Introducing Web Performance.md",
                "collapseAll": false,
                "extraContext": false,
                "sortOrder": "alphabetical",
                "showSearch": false,
                "searchQuery": "",
                "backlinkCollapsed": false,
                "unlinkedCollapsed": true
              },
              "icon": "links-coming-in",
              "title": "Backlinks for Introducing Web Performance"
            }
          },
          {
            "id": "d9590bf5082ae573",
            "type": "leaf",
            "state": {
              "type": "outgoing-link",
              "state": {
                "file": "Programs/JS-Performance/Introducing Web Performance.md",
                "linksCollapsed": false,
                "unlinkedCollapsed": true
              },
              "icon": "links-going-out",
              "title": "Outgoing links from Introducing Web Performance"
            }
          },
          {
            "id": "a93296f15b8b91ac",
            "type": "leaf",
            "state": {
              "type": "tag",
              "state": {
                "sortOrder": "frequency",
                "useHierarchy": true
              },
              "icon": "lucide-tags",
              "title": "Tags"
            }
          },
          {
            "id": "52484d27535465e3",
            "type": "leaf",
            "state": {
              "type": "outline",
              "state": {
                "file": "Programs/JS-Performance/Introducing Web Performance.md"
              },
              "icon": "lucide-list",
              "title": "Outline of Introducing Web Performance"
            }
          },
          {
            "id": "cfa6b0aecced3b96",
            "type": "leaf",
            "state": {
              "type": "all-properties",
              "state": {
                "sortOrder": "frequency",
                "showSearch": false,
                "searchQuery": ""
              },
              "icon": "lucide-archive",
              "title": "All properties"
            }
          },
          {
            "id": "b7cb9d1ff24d7641",
            "type": "leaf",
            "state": {
              "type": "advanced-tables-toolbar",
              "state": {},
              "icon": "spreadsheet",
              "title": "Advanced Tables"
            }
          }
        ],
        "currentTab": 5
      }
    ],
    "direction": "horizontal",
    "width": 300,
    "collapsed": true
  },
  "left-ribbon": {
    "hiddenItems": {
      "switcher:Open quick switcher": false,
      "graph:Open graph view": false,
      "canvas:Create new canvas": false,
      "daily-notes:Open today's daily note": false,
      "templates:Insert template": false,
      "command-palette:Open command palette": false,
      "table-editor-obsidian:Advanced Tables Toolbar": false,
      "publish:Publish changes...": false
    }
  },
  "active": "46809242ae41aa57",
  "lastOpenFiles": [
    "Areas/English/Grammar - BritishCouncil/Verb Forms.md",
    "Areas/English/Interacting with people at work/Clear and to the point.md",
    "Areas/English/Interacting with people at work",
    "Areas/English/Grammar - BritishCouncil/Countable and Uncountable Nouns.md",
    "Areas/English/Grammar - BritishCouncil/Get your articles right.md",
    "Areas/English/Grammar - BritishCouncil/All about adjectives.md",
    "Areas/English/Grammar B2/Countable and uncountable nouns.md",
    "Areas/English/Grammar - BritishCouncil",
    "Areas/English/Grammar B2/Relative Clause Reduction Rules.md",
    "Areas/English/Grammar B2/Compound nouns.md",
    "Areas/English/Grammar B2/Adjectives as nouns.md",
    "Areas/English/Grammars",
    "Areas/English/Info writing unit1.png",
    "Areas/English/Relative Clause Reduction Rules.md",
    "Areas/English/Notes.md",
    "Areas/English/Listening Tips.md",
    "Areas/Programming/Dockers/Introduction to Docker.md",
    "Areas/Programming/Dockers/Advance Containers.md",
    "Archives/Secrets.md",
    "Areas/Programming/Security/XSS (Cross-Site Scripting).md",
    "Areas/Programming/Design Patterns/OOP.md",
    "Areas/Programming/Design Patterns/README.md",
    "Areas/Programming/Design Patterns/Abstract Factory.md",
    "Areas/Programming/Design Patterns/Observer.md",
    "Areas/Programming/Design Patterns/Prototype.md",
    "Areas/Programming/Design Patterns/Proxy.md",
    "Areas/Programming/Functional Programming/Functional Programming.md",
    "Areas/Programming/Functional Programming/Chapter 3. Few data structures, many operations.md",
    "Areas/Programming/Functional Programming/FP-Arch-Class.pdf",
    "Areas/Programming/Design Patterns/images/FactoryMethodPattern-2.png",
    "Areas/Programming/Design Patterns/images/FactoryMethodPattern-1.png",
    "Areas/Programming/Design Patterns/images/Design-Principles-5.png",
    "Areas/Programming/Design Patterns/images/Design-Principles-4.png",
    "Areas/Programming/Design Patterns/images/Design-Principles-3.png",
    "Areas/Programming/Design Patterns/images/Design-Principles-2.png",
    "Areas/Programming/Design Patterns/images/Design-Principles-1.png",
    "Areas/Programming/Design Patterns/Untitled.md",
    "Areas/Programming/Design Patterns/Design Patterns For Dummies/Summarise.md",
    "Areas/Programming/Design Patterns/Design Patterns For Dummies/Design Patterns For Dummies.pdf",
    "Projects",
    "Untitled.canvas",
    "Resources",
    "Areas/Programming",
    "Areas",
    "Archives",
    "Areas/Programming/Design Patterns/images/OOP-UML-9.png",
    "Areas/Programming/Design Patterns/images/OOP-UML-8.png"
  ]
}